Workbook

Sheet Instructions
A1: MoneyKiBaatein – Bank Reconciliation Practice Project
A2: Objective | B2: Practice a real-world accountant workflow: Books vs Bank Statement reconciliation.
A3: Step 1 | B3: Review Books_Data and Bank_Data.
A4: Step 2 | B4: Compare transaction reference numbers and amounts.
A5: Step 3 | B5: Complete the Reconciliation sheet.
A6: Step 4 | B6: Identify matched, outstanding, bank-only and amount-difference items.
A7: Step 5 | B7: Review the Summary sheet.
A8: Portfolio Use | B8: This workbook uses fictional data and can be uploaded to GitHub as an accounting portfolio project.
A9: Privacy | B9: Do not upload confidential employer/client bank data to GitHub.

Sheet Books_Data
A1: Date | B1: Ref No | C1: Description | D1: Debit | E1: Credit | F1: Amount
A2: 46266 | B2: BR-001 | C2: Customer Receipt – ABC Traders | D2: 0 | E2: 25000 | F2: 25000
A3: 46267 | B3: BR-002 | C3: Vendor Payment – XYZ Suppliers | D3: 15000 | E3: 0 | F3: 15000
A4: 46268 | B4: BR-003 | C4: Office Rent | D4: 12000 | E4: 0 | F4: 12000
A5: 46269 | B5: BR-004 | C5: Customer Receipt – PQR Ltd | D5: 0 | E5: 30000 | F5: 30000
A6: 46270 | B6: BR-005 | C6: Bank Charges | D6: 0 | E6: 0 | F6: 500
A7: 46271 | B7: BR-006 | C7: Vendor Payment – LMN Traders | D7: 18000 | E7: 0 | F7: 18000
A8: 46272 | B8: BR-007 | C8: Customer Receipt – DEF Ltd | D8: 0 | E8: 22000 | F8: 22000
A9: 46273 | B9: BR-008 | C9: Cheque Issued – GHI Services | D9: 10000 | E9: 0 | F9: 10000
A10: 46274 | B10: BR-009 | C10: Customer Receipt – JKL Pvt Ltd | D10: 0 | E10: 15000 | F10: 15000
A11: 46275 | B11: BR-010 | C11: Electricity Expense | D11: 6500 | E11: 0 | F11: 6500

Sheet Bank_Data
A1: Date | B1: Ref No | C1: Description | D1: Debit | E1: Credit | F1: Amount
A2: 46266 | B2: BR-001 | C2: Customer Receipt – ABC Traders | D2: 0 | E2: 25000 | F2: 25000
A3: 46267 | B3: BR-002 | C3: Vendor Payment – XYZ Suppliers | D3: 15000 | E3: 0 | F3: 15000
A4: 46268 | B4: BR-003 | C4: Office Rent | D4: 12000 | E4: 0 | F4: 12000
A5: 46269 | B5: BR-004 | C5: Customer Receipt – PQR Ltd | D5: 0 | E5: 30000 | F5: 30000
A6: 46270 | B6: BC-001 | C6: Bank Charges | D6: 500 | E6: 0 | F6: 500
A7: 46272 | B7: BR-007 | C7: Customer Receipt – DEF Ltd | D7: 0 | E7: 22000 | F7: 22000
A8: 46274 | B8: BR-009 | C8: Customer Receipt – JKL Pvt Ltd | D8: 0 | E8: 15000 | F8: 15000
A9: 46276 | B9: BC-002 | C9: Direct Bank Credit – Customer | D9: 0 | E9: 8000 | F9: 8000
A10: 46277 | B10: BR-010 | C10: Electricity Expense | D10: 6500 | E10: 0 | F10: 6500
A11: 46278 | B11: BC-003 | C11: Bank Interest | D11: 0 | E11: 1200 | F11: 1200

Sheet Reconciliation
A1: Book Ref | B1: Book Amount | C1: Bank Ref | D1: Bank Amount | E1: Status | F1: Difference | G1: Remarks
A2: =Books_Data!B2 | B2: =Books_Data!F2 | C2: =IFERROR(VLOOKUP(A2,Bank_Data!B:F,1,FALSE),"") | D2: =IFERROR(VLOOKUP(A2,Bank_Data!B:F,5,FALSE),"") | E2: =IF(C2="","Outstanding in Bank",IF(B2=D2,"Matched","Amount Difference")) | F2: =IF(D2="","",B2-D2) | G2: =IF(E2="Matched","No action",IF(E2="Outstanding in Bank","Check whether transaction is pending/uncleared","Investigate difference"))
A3: =Books_Data!B3 | B3: =Books_Data!F3 | C3: =IFERROR(VLOOKUP(A3,Bank_Data!B:F,1,FALSE),"") | D3: =IFERROR(VLOOKUP(A3,Bank_Data!B:F,5,FALSE),"") | E3: =IF(C3="","Outstanding in Bank",IF(B3=D3,"Matched","Amount Difference")) | F3: =IF(D3="","",B3-D3) | G3: =IF(E3="Matched","No action",IF(E3="Outstanding in Bank","Check whether transaction is pending/uncleared","Investigate difference"))
A4: =Books_Data!B4 | B4: =Books_Data!F4 | C4: =IFERROR(VLOOKUP(A4,Bank_Data!B:F,1,FALSE),"") | D4: =IFERROR(VLOOKUP(A4,Bank_Data!B:F,5,FALSE),"") | E4: =IF(C4="","Outstanding in Bank",IF(B4=D4,"Matched","Amount Difference")) | F4: =IF(D4="","",B4-D4) | G4: =IF(E4="Matched","No action",IF(E4="Outstanding in Bank","Check whether transaction is pending/uncleared","Investigate difference"))
A5: =Books_Data!B5 | B5: =Books_Data!F5 | C5: =IFERROR(VLOOKUP(A5,Bank_Data!B:F,1,FALSE),"") | D5: =IFERROR(VLOOKUP(A5,Bank_Data!B:F,5,FALSE),"") | E5: =IF(C5="","Outstanding in Bank",IF(B5=D5,"Matched","Amount Difference")) | F5: =IF(D5="","",B5-D5) | G5: =IF(E5="Matched","No action",IF(E5="Outstanding in Bank","Check whether transaction is pending/uncleared","Investigate difference"))
A6: =Books_Data!B6 | B6: =Books_Data!F6 | C6: =IFERROR(VLOOKUP(A6,Bank_Data!B:F,1,FALSE),"") | D6: =IFERROR(VLOOKUP(A6,Bank_Data!B:F,5,FALSE),"") | E6: =IF(C6="","Outstanding in Bank",IF(B6=D6,"Matched","Amount Difference")) | F6: =IF(D6="","",B6-D6) | G6: =IF(E6="Matched","No action",IF(E6="Outstanding in Bank","Check whether transaction is pending/uncleared","Investigate difference"))
A7: =Books_Data!B7 | B7: =Books_Data!F7 | C7: =IFERROR(VLOOKUP(A7,Bank_Data!B:F,1,FALSE),"") | D7: =IFERROR(VLOOKUP(A7,Bank_Data!B:F,5,FALSE),"") | E7: =IF(C7="","Outstanding in Bank",IF(B7=D7,"Matched","Amount Difference")) | F7: =IF(D7="","",B7-D7) | G7: =IF(E7="Matched","No action",IF(E7="Outstanding in Bank","Check whether transaction is pending/uncleared","Investigate difference"))
A8: =Books_Data!B8 | B8: =Books_Data!F8 | C8: =IFERROR(VLOOKUP(A8,Bank_Data!B:F,1,FALSE),"") | D8: =IFERROR(VLOOKUP(A8,Bank_Data!B:F,5,FALSE),"") | E8: =IF(C8="","Outstanding in Bank",IF(B8=D8,"Matched","Amount Difference")) | F8: =IF(D8="","",B8-D8) | G8: =IF(E8="Matched","No action",IF(E8="Outstanding in Bank","Check whether transaction is pending/uncleared","Investigate difference"))
A9: =Books_Data!B9 | B9: =Books_Data!F9 | C9: =IFERROR(VLOOKUP(A9,Bank_Data!B:F,1,FALSE),"") | D9: =IFERROR(VLOOKUP(A9,Bank_Data!B:F,5,FALSE),"") | E9: =IF(C9="","Outstanding in Bank",IF(B9=D9,"Matched","Amount Difference")) | F9: =IF(D9="","",B9-D9) | G9: =IF(E9="Matched","No action",IF(E9="Outstanding in Bank","Check whether transaction is pending/uncleared","Investigate difference"))
A10: =Books_Data!B10 | B10: =Books_Data!F10 | C10: =IFERROR(VLOOKUP(A10,Bank_Data!B:F,1,FALSE),"") | D10: =IFERROR(VLOOKUP(A10,Bank_Data!B:F,5,FALSE),"") | E10: =IF(C10="","Outstanding in Bank",IF(B10=D10,"Matched","Amount Difference")) | F10: =IF(D10="","",B10-D10) | G10: =IF(E10="Matched","No action",IF(E10="Outstanding in Bank","Check whether transaction is pending/uncleared","Investigate difference"))
A11: =Books_Data!B11 | B11: =Books_Data!F11 | C11: =IFERROR(VLOOKUP(A11,Bank_Data!B:F,1,FALSE),"") | D11: =IFERROR(VLOOKUP(A11,Bank_Data!B:F,5,FALSE),"") | E11: =IF(C11="","Outstanding in Bank",IF(B11=D11,"Matched","Amount Difference")) | F11: =IF(D11="","",B11-D11) | G11: =IF(E11="Matched","No action",IF(E11="Outstanding in Bank","Check whether transaction is pending/uncleared","Investigate difference"))
A14: BANK-ONLY ITEMS
A15: Bank Ref | B15: Amount | C15: Description | D15: Suggested Action
A16: BC-002 | B16: 8000 | C16: Direct Bank Credit – Customer | D16: Record in books after verification
A17: BC-003 | B17: 1200 | C17: Bank Interest | D17: Record bank interest in books
A18: BC-001 | B18: 500 | C18: Bank Charges | D18: Record bank charges in books / verify if already booked

Sheet Summary
A1: Bank Reconciliation Summary
A2: Metric | B2: Value
A3: Total Book Transactions | B3: =COUNTA(Books_Data!B2:B11)
A4: Matched Transactions | B4: =COUNTIF(Reconciliation!E2:E11,"Matched")
A5: Outstanding in Bank | B5: =COUNTIF(Reconciliation!E2:E11,"Outstanding in Bank")
A6: Amount Difference | B6: =COUNTIF(Reconciliation!E2:E11,"Amount Difference")
A7: Bank-only Items | B7: =COUNTA(Reconciliation!A16:A18)
A8: Total Book Amount | B8: =SUM(Books_Data!F2:F11)
A9: Total Bank Amount | B9: =SUM(Bank_Data!F2:F11)
A10: Portfolio Note | B10: Fictional data for learning and portfolio practice.
